cryptopi/__init__.py
cryptopi/utils.py
cryptopi/api/__init__.py
cryptopi/api/api.py
cryptopi/api/urls/__init__.py
cryptopi/api/urls/data.py
cryptopi/api/urls/interface.py
cryptopi/api/urls/paths.py
cryptopi/api/urls/responses.py
cryptopi/api/urls/utils.py
cryptopi/api/urls/requests/__init__.py
cryptopi/api/urls/requests/definitions.py
cryptopi/api/urls/requests/models.py
cryptopi/api/urls/requests/values.py
cryptopi/integration_tests/__init__.py
cryptopi/integration_tests/test_cryptocurrencies.py
cryptopi/models/__init__.py
cryptopi-0.0.14.dist-info/LICENCE
cryptopi-0.0.14.dist-info/METADATA
cryptopi-0.0.14.dist-info/WHEEL
cryptopi-0.0.14.dist-info/top_level.txt
cryptopi-0.0.14.dist-info/RECORD
